ceresfit/__init__.py
ceresfit/ceresfit_linreg.py
ceresfit/unc_calc.py
ceresfit-0.3.2.dist-info/METADATA
ceresfit-0.3.2.dist-info/WHEEL
ceresfit-0.3.2.dist-info/licenses/LICENSE
ceresfit-0.3.2.dist-info/RECORD
